shaphinx/__init__.py
shaphinx/navigation.py
shaphinx/sphinxext.py
shaphinx/theme/.DS_Store
shaphinx/theme/__init__.py
shaphinx/theme/shaphinx/.DS_Store
shaphinx/theme/shaphinx/__init__.py
shaphinx/theme/shaphinx/base.html
shaphinx/theme/shaphinx/domainindex.html
shaphinx/theme/shaphinx/genindex.html
shaphinx/theme/shaphinx/globaltoc.html
shaphinx/theme/shaphinx/layout.html
shaphinx/theme/shaphinx/localtoc.html
shaphinx/theme/shaphinx/page.html
shaphinx/theme/shaphinx/search.html
shaphinx/theme/shaphinx/theme.conf
shaphinx/theme/shaphinx/partials/_head_css_variables.html
shaphinx/theme/shaphinx/partials/icons.html
shaphinx/theme/shaphinx/sidebar/brand.html
shaphinx/theme/shaphinx/sidebar/ethical-ads.html
shaphinx/theme/shaphinx/sidebar/navigation.html
shaphinx/theme/shaphinx/sidebar/rtd-versions.html
shaphinx/theme/shaphinx/sidebar/scroll-end.html
shaphinx/theme/shaphinx/sidebar/scroll-start.html
shaphinx/theme/shaphinx/sidebar/search.html
shaphinx/theme/shaphinx/static/.DS_Store
shaphinx/theme/shaphinx/static/scripts/main.js
shaphinx/theme/shaphinx/static/scripts/main.js.map
shaphinx/theme/shaphinx/static/styles/shaphinx-extensions.css
shaphinx/theme/shaphinx/static/styles/shaphinx-extensions.css.map
shaphinx/theme/shaphinx/static/styles/shaphinx.css
shaphinx/theme/shaphinx/static/styles/shaphinx.css.map
shaphinx-0.1.3.dist-info/METADATA
shaphinx-0.1.3.dist-info/RECORD
shaphinx-0.1.3.dist-info/WHEEL
shaphinx-0.1.3.dist-info/entry_points.txt
shaphinx-0.1.3.dist-info/top_level.txt
