Metadata-Version: 2.1
Name: shaphinx
Version: 0.1.3
Summary: Just a sphinx theme.
Home-page: https://github.com/llango/shaphinx
Author: rontom
Author-email: rontomai@gmail.com
License: MIT license
Keywords: shaphinx
Platform: UNKNOWN
Classifier: Development Status :: 2 - Pre-Alpha
Classifier: Intended Audience :: Developers
Classifier: License :: OSI Approved :: MIT License
Classifier: Natural Language :: English
Classifier: Programming Language :: Python :: 3
Classifier: Programming Language :: Python :: 3.5
Classifier: Programming Language :: Python :: 3.6
Classifier: Programming Language :: Python :: 3.7
Classifier: Programming Language :: Python :: 3.8
Requires-Python: >=3.5
Requires-Dist: Click (>=7.0)
